{
  "parent": "minecraft:recipes/root",
  "criteria": {
    "has_stack_upgrade_tier_4": {
      "conditions": {
        "items": [
          {
            "items": "sophisticatedstorage:stack_upgrade_tier_5"
          }
        ]
      },
      "trigger": "minecraft:inventory_changed"
    },
    "has_the_recipe": {
      "conditions": {
        "recipe": "sophisticated_emerald_upgrade:stack_upgrade_tier_ss_6"
      },
      "trigger": "minecraft:recipe_unlocked"
    }
  },
  "requirements": [
    [
      "has_the_recipe",
      "has_stack_upgrade_tier_4"
    ]
  ],
  "rewards": {
    "recipes": [
      "sophisticated_emerald_upgrade:stack_upgrade_tier_ss_6"
    ]
  }
}